SAC_Tello/__init__.py
SAC_Tello/aruco_detector.py
SAC_Tello/face_recognition.py
SAC_Tello/tello_aruco_hud.py
SAC_Tello/tello_cmd.py
SAC_Tello/tello_drone.py
SAC_Tello/tello_face_hud.py
SAC_Tello/tello_hud.py
SAC_Tello/tello_rc.py
SAC_Tello/tello_remote.py
SAC_Tello/tello_state.py
SAC_Tello/tello_video.py
SAC_Tello/models/face_detection_yunet_2023mar.onnx
SAC_Tello/models/face_recognition_sface_2021dec.onnx
sac_tello-0.1.11.dist-info/METADATA
sac_tello-0.1.11.dist-info/WHEEL
sac_tello-0.1.11.dist-info/licenses/LICENSE
sac_tello-0.1.11.dist-info/RECORD
