Metadata-Version: 2.3
Name: SAC-Tello
Version: 0.1.11
Summary: A Python-based DJI Tello interface. Created primaily for educational use.
Project-URL: Homepage, https://github.com/xLeachimx/SAC-Tello
Project-URL: Bug Tracker, https://github.com/xLeachimx/SAC-Tello/issues
Author-email: Michael Huelsman <michael.huelsman@gmail.com>
License:                     GNU GENERAL PUBLIC LICENSE
License-File: LICENSE
Classifier: Operating System :: OS Independent
Classifier: Programming Language :: Python :: 3
Requires-Python: >=3.11
Requires-Dist: numpy>=1.23.4
Requires-Dist: opencv-python>=4.10.0.84
Requires-Dist: pygame>=2.5.0
